README.rst
setup.py
lynkz/__init__.py
lynkz/lynkz.py
lynkz.egg-info/PKG-INFO
lynkz.egg-info/SOURCES.txt
lynkz.egg-info/dependency_links.txt
lynkz.egg-info/not-zip-safe
lynkz.egg-info/requires.txt
lynkz.egg-info/top_level.txt