Metadata-Version: 1.0
Name: lynkz
Version: 1.3
Summary: Unofficial Python wrapper for the lynkz.me API
Home-page: https://github.com/Ewpratten/lynkz
Author: Evan Pratten
Author-email: ewpratten@gmail.com
License: MIT
Platform: UNKNOWN
